hcl_model/__init__.py
hcl_model/labels.py
hcl_model/model_base.py
hcl_model/model_hcl_generic.py
hcl_model/model_sarimax.py
hcl_model/transformers/__init__.py
hcl_model/transformers/add_automatic_seasonal_dummies.py
hcl_model/transformers/add_holiday_dummies.py
hcl_model/transformers/add_holiday_triangles.py
hcl_model/transformers/add_periodic_splines.py
hcl_model/transformers/estimator_to_transformer.py
hcl_model/transformers/feature_union.py
hcl_model/transformers/outlier_correction.py
hcl_model/transformers/series_to_frame.py
hcl_model/transformers/structural_breaks.py
hcl_model/transformers/truncate.py
hcl_model/utils/__init__.py
hcl_model/utils/calendar_reader.py
hcl_model/utils/check_x_y.py
hcl_model/utils/construct_calendar_exogenous.py
hcl_model/utils/decayed_weights.py
hcl_model/utils/get_duplicate_columns.py
hcl_model/utils/smooth.py
hcl_model/utils/string_enum.py
hcl_model-0.6.2.dist-info/AUTHORS.md
hcl_model-0.6.2.dist-info/LICENSE
hcl_model-0.6.2.dist-info/METADATA
hcl_model-0.6.2.dist-info/WHEEL
hcl_model-0.6.2.dist-info/top_level.txt
hcl_model-0.6.2.dist-info/RECORD
