Metadata-Version: 2.1
Name: hcl-model
Version: 0.6.2
Summary: Simple time series forecasting based on multiple linear regression
Home-page: https://github.com/khrapovs/hcl-model
Author: Stanislav Khrapov
Author-email: stanislav.khrapov@dbschenker.com
License: MIT
Project-URL: PyPi, https://pypi.org/project/hcl-model/
Platform: any
Classifier: Development Status :: 4 - Beta
Classifier: Programming Language :: Python
Classifier: Programming Language :: Python :: 3.7
Classifier: Programming Language :: Python :: 3.8
Classifier: Programming Language :: Python :: 3.9
Requires-Python: <3.10,>=3.7
License-File: LICENSE
License-File: AUTHORS.md
Requires-Dist: sklearn
Requires-Dist: numpy
Requires-Dist: pandas (>=1.1)
Requires-Dist: statsmodels
Requires-Dist: ruptures
Requires-Dist: scipy (>=1.5)
Requires-Dist: workalendar (>=10.0.0)
Provides-Extra: deploy
Requires-Dist: wheel ; extra == 'deploy'
Requires-Dist: build ; extra == 'deploy'
Requires-Dist: twine ; extra == 'deploy'
Provides-Extra: dev
Requires-Dist: black ; extra == 'dev'
Requires-Dist: pre-commit ; extra == 'dev'
Provides-Extra: doc
Requires-Dist: mkdocs ; extra == 'doc'
Requires-Dist: pymdown-extensions ; extra == 'doc'
Provides-Extra: test
Requires-Dist: pytest ; extra == 'test'
Requires-Dist: pytest-cov ; extra == 'test'
